odoo/addons/web_font_arial/LICENSE
odoo/addons/web_font_arial/README.rst
odoo/addons/web_font_arial/__init__.py
odoo/addons/web_font_arial/__manifest__.py
odoo/addons/web_font_arial/models/__init__.py
odoo/addons/web_font_arial/models/res_company.py
odoo/addons/web_font_arial/static/description/icon.png
odoo/addons/web_font_arial/static/description/index.html
odoo_addon_web_font_arial-16.0.1.0.0.dist-info/METADATA
odoo_addon_web_font_arial-16.0.1.0.0.dist-info/WHEEL
odoo_addon_web_font_arial-16.0.1.0.0.dist-info/top_level.txt
odoo_addon_web_font_arial-16.0.1.0.0.dist-info/RECORD
